pytest_covid/__init__.py
pytest_covid-0.0.5.dist-info/entry_points.txt
pytest_covid-0.0.5.dist-info/LICENSE
pytest_covid-0.0.5.dist-info/WHEEL
pytest_covid-0.0.5.dist-info/METADATA
pytest_covid-0.0.5.dist-info/RECORD
