Metadata-Version: 2.1
Name: pytest_covid
Version: 0.0.5
Summary: Too many faillure, less tests.
Home-page: https://pypi.org/project/pytest_covid/
License: UNKNOWN
Author: Matthias Bussonnier
Author-email: bussonniermatthias@gmail.com
Requires-Python: >=3.6
Classifier: License :: OSI Approved :: MIT License
Classifier: Intended Audience :: Developers
Classifier: Programming Language :: Python :: 3
Classifier: Framework :: Pytest
Project-URL: Source, https://github.com/Carreau/pytest_covid
